grAdapt/__init__.py
grAdapt/datasets/__init__.py
grAdapt/datasets/testfunctions/__init__.py
grAdapt/datasets/testfunctions/bivariate.py
grAdapt/datasets/testfunctions/multivariate.py
grAdapt/escape/CMAES.py
grAdapt/escape/MatyasNormalDistribution.py
grAdapt/escape/MaxStandardDeviation.py
grAdapt/escape/NormalDistribution.py
grAdapt/escape/NormalDistributionDecay.py
grAdapt/escape/StandardNormalDistribution.py
grAdapt/escape/UniformDistribution.py
grAdapt/escape/__init__.py
grAdapt/escape/base.py
grAdapt/models/Asynchronous.py
grAdapt/models/Sequential.py
grAdapt/models/__init__.py
grAdapt/optimizer/AMSGradBisection.py
grAdapt/optimizer/AdaGradBisection.py
grAdapt/optimizer/AdaMaxBisection.py
grAdapt/optimizer/AdamBisection.py
grAdapt/optimizer/GradientDescentBisection.py
grAdapt/optimizer/MomentumBisection.py
grAdapt/optimizer/RMSPropBisection.py
grAdapt/optimizer/__init__.py
grAdapt/optimizer/base.py
grAdapt/sampling/__init__.py
grAdapt/sampling/equidistributed/Density.py
grAdapt/sampling/equidistributed/KDistance.py
grAdapt/sampling/equidistributed/KDistanceMean.py
grAdapt/sampling/equidistributed/MaximalMinDistance.py
grAdapt/sampling/equidistributed/Mitchell.py
grAdapt/sampling/equidistributed/Reassignment.py
grAdapt/sampling/equidistributed/__init__.py
grAdapt/sampling/equidistributed/base.py
grAdapt/sampling/initializer/Uniform.py
grAdapt/sampling/initializer/Vertices.py
grAdapt/sampling/initializer/VerticesForce.py
grAdapt/sampling/initializer/VerticesForceRandom.py
grAdapt/sampling/initializer/__init__.py
grAdapt/sampling/initializer/base.py
grAdapt/space/__init__.py
grAdapt/space/datatype/Categorical.py
grAdapt/space/datatype/Float.py
grAdapt/space/datatype/Integer.py
grAdapt/space/datatype/Nominal.py
grAdapt/space/datatype/Ordinal.py
grAdapt/space/datatype/__init__.py
grAdapt/space/datatype/base.py
grAdapt/space/transformer/Transformer.py
grAdapt/space/transformer/__init__.py
grAdapt/surrogate/GPR.py
grAdapt/surrogate/NoGradient.py
grAdapt-0.1.1b8.dist-info/LICENSE
grAdapt-0.1.1b8.dist-info/METADATA
grAdapt-0.1.1b8.dist-info/WHEEL
grAdapt-0.1.1b8.dist-info/top_level.txt
grAdapt-0.1.1b8.dist-info/RECORD
