Metadata-Version: 2.1
Name: grAdapt
Version: 0.1.1b8
Summary: grAdapt: Gradient Adaption for Black-Box Optimization.
Home-page: https://github.com/mkduong-ai/grAdapt
Author: Manh Khoi Duong
Author-email: manh.duong@hhu.de
License: Apache License 2.0
Download-URL: https://github.com/mkduong-ai/grAdapt/blob/master/dist/grAdapt-0.1.1b6.tar.gz?raw=true
Keywords: grAdapt,black-box optimization,optimization,smbo,hyperparameter optimization,hyperparameter,sequential model-based optimization,stochastic optimization,global optimization,machine learning,toolbox
Platform: UNKNOWN
Classifier: Programming Language :: Python :: 3.6
Classifier: Programming Language :: Python :: 3.7
Classifier: Programming Language :: Python :: 3.8
Classifier: License :: OSI Approved :: Apache Software License
Classifier: Operating System :: OS Independent
Requires-Dist: numpy (~=1.18)
Requires-Dist: scipy (~=1.4)
Requires-Dist: scikit-learn (~=0.22)
Requires-Dist: tqdm (~=4.44)
Requires-Dist: deprecated (~=1.2.7)
